structlog_round/__init__.py
structlog_round/processor.py
structlog_round-1.0.dist-info/LICENSE
structlog_round-1.0.dist-info/METADATA
structlog_round-1.0.dist-info/WHEEL
structlog_round-1.0.dist-info/top_level.txt
structlog_round-1.0.dist-info/RECORD
