Metadata-Version: 2.1
Name: structlog-round
Version: 1.0
Summary: A light-weight structlog processor to round floats for prettier logging.
Home-page: https://github.com/stefanbschneider/structlog-round
Author: Stefan Schneider
License: UNKNOWN
Platform: UNKNOWN
Classifier: Programming Language :: Python :: 3
Classifier: License :: OSI Approved :: MIT License
Classifier: Operating System :: OS Independent
Requires-Python: >=3.6
Requires-Dist: structlog
Provides-Extra: dev
Requires-Dist: pytest ; extra == 'dev'
Requires-Dist: numpy ; extra == 'dev'
Provides-Extra: tests
Requires-Dist: pytest ; extra == 'tests'
Requires-Dist: numpy ; extra == 'tests'
